django_filebased_email_backend_ng/__init__.py
django_filebased_email_backend_ng/backend.py
django_filebased_email_backend_ng-2.1.3.dist-info/COPYING
django_filebased_email_backend_ng-2.1.3.dist-info/METADATA
django_filebased_email_backend_ng-2.1.3.dist-info/WHEEL
django_filebased_email_backend_ng-2.1.3.dist-info/top_level.txt
django_filebased_email_backend_ng-2.1.3.dist-info/RECORD
