Metadata-Version: 2.1
Name: django-filebased-email-backend-ng
Version: 2.1.3
Summary: A better 'file' email backend for Django
Home-page: https://chris-lamb.co.uk/projects/django-filebased-email-backend-ng
Author: Chris Lamb
Author-email: chris@chris-lamb.co.uk
License: BSD
Platform: UNKNOWN
License-File: COPYING
Requires-Dist: Django (>=1.8)
